paraview_mcp/__init__.py
paraview_mcp/paraview_manager.py
paraview_mcp/paraview_mcp_server.py
paraview_mcp-0.1.1.dist-info/licenses/LICENSE
paraview_mcp-0.1.1.dist-info/licenses/NOTICE
paraview_mcp-0.1.1.dist-info/METADATA
paraview_mcp-0.1.1.dist-info/WHEEL
paraview_mcp-0.1.1.dist-info/entry_points.txt
paraview_mcp-0.1.1.dist-info/top_level.txt
paraview_mcp-0.1.1.dist-info/RECORD
