Metadata-Version: 2.4
Name: paraview-mcp
Version: 0.1.1
Summary: MCP (Model Context Protocol) server for ParaView visualization control
Home-page: https://github.com/LLNL/paraview_mcp
Author: Shusen Liu and Haichao Miao
Author-email: Shusen Liu <liu42@llnl.gov>, Haichao Miao <miao1@llnl.gov>
Maintainer-email: Shusen Liu <liu42@llnl.gov>, Haichao Miao <miao1@llnl.gov>
License: MIT
Project-URL: Homepage, https://github.com/LLNL/paraview_mcp
Project-URL: Documentation, https://paraview-mcp.readthedocs.io
Project-URL: Repository, https://github.com/LLNL/paraview_mcp
Project-URL: Issues, https://github.com/LLNL/paraview_mcp/issues
Classifier: Development Status :: 3 - Alpha
Classifier: Intended Audience :: Science/Research
Classifier: Topic :: Scientific/Engineering :: Visualization
Classifier: License :: OSI Approved :: MIT License
Classifier: Programming Language :: Python :: 3
Classifier: Programming Language :: Python :: 3.8
Classifier: Programming Language :: Python :: 3.9
Classifier: Programming Language :: Python :: 3.10
Classifier: Programming Language :: Python :: 3.11
Classifier: Operating System :: OS Independent
Requires-Python: >=3.8
License-File: LICENSE
License-File: NOTICE
Requires-Dist: mcp>=0.1.0
Requires-Dist: Pillow>=9.0.0
Provides-Extra: dev
Requires-Dist: pytest>=7.0.0; extra == "dev"
Requires-Dist: pytest-asyncio>=0.21.0; extra == "dev"
Requires-Dist: black>=22.0.0; extra == "dev"
Requires-Dist: flake8>=5.0.0; extra == "dev"
Requires-Dist: mypy>=0.990; extra == "dev"
Requires-Dist: pre-commit>=3.0.0; extra == "dev"
Provides-Extra: eval
Requires-Dist: promptfoo>=0.118.0; extra == "eval"
Requires-Dist: anthropic>=0.34.0; extra == "eval"
Requires-Dist: openai>=1.0.0; extra == "eval"
Requires-Dist: python-dotenv>=1.0.0; extra == "eval"
Provides-Extra: docs
Requires-Dist: sphinx>=5.0.0; extra == "docs"
Requires-Dist: sphinx-rtd-theme>=1.2.0; extra == "docs"
Requires-Dist: sphinx-autodoc-typehints>=1.19.0; extra == "docs"
Dynamic: author
Dynamic: home-page
Dynamic: license-file
Dynamic: requires-python
